clutchtimealerts/__init__.py
clutchtimealerts/__main__.py
clutchtimealerts/clutch_alerts.py
clutchtimealerts/config_parser.py
clutchtimealerts/db_utils.py
clutchtimealerts/format_utils.py
clutchtimealerts/notification_collector.py
clutchtimealerts/notifications/__init__.py
clutchtimealerts/notifications/base.py
clutchtimealerts/notifications/groupme.py
clutchtimealerts/notifications/ntfy.py
clutchtimealerts/notifications/slack.py
clutchtimealerts/notifications/twilio.py
clutchtimealerts/scraper/__init__.py
clutchtimealerts/scraper/live_scores.py
clutchtimealerts-0.2.2.dist-info/licenses/LICENSE
clutchtimealerts-0.2.2.dist-info/METADATA
clutchtimealerts-0.2.2.dist-info/WHEEL
clutchtimealerts-0.2.2.dist-info/top_level.txt
clutchtimealerts-0.2.2.dist-info/RECORD
