Metadata-Version: 2.4
Name: clutchtimealerts
Version: 0.2.2
Summary: Default template for PDM package
Author-email: Brian Walheim <bri125521@gmail.com>
License: MIT
Requires-Python: >=3.9
License-File: LICENSE
Requires-Dist: requests>=2.32.3
Requires-Dist: slack-sdk>=3.34.0
Requires-Dist: pyyaml>=6.0.2
Requires-Dist: twilio>=9.4.1
Requires-Dist: sqlalchemy>=2.0.36
Dynamic: license-file
